{"trial_id": "7d34e0de4c862134c1d41703439d428d", "hyperparameters": {"space": [{"class_name": "Int", "config": {"name": "num_layers", "default": null, "conditions": [], "min_value": 1, "max_value": 4, "step": 1, "sampling": null}}, {"class_name": "Int", "config": {"name": "units_0", "default": null, "conditions": [], "min_value": 32, "max_value": 608, "step": 32, "sampling": null}}, {"class_name": "Int", "config": {"name": "units_1", "default": null, "conditions": [], "min_value": 32, "max_value": 608, "step": 32, "sampling": null}}, {"class_name": "Int", "config": {"name": "units_2", "default": null, "conditions": [], "min_value": 32, "max_value": 608, "step": 32, "sampling": null}}, {"class_name": "Int", "config": {"name": "units_3", "default": null, "conditions": [], "min_value": 32, "max_value": 608, "step": 32, "sampling": null}}], "values": {"num_layers": 3, "units_0": 224, "units_1": 160, "units_2": 384, "units_3": 448, "tuner/epochs": 17, "tuner/initial_epoch": 0, "tuner/bracket": 1, "tuner/round": 0}}, "metrics": {"metrics": {"loss": {"direction": "min", "observations": [{"value": [1867.3997802734375], "step": 0}]}, "mean_squared_error": {"direction": "min", "observations": [{"value": [1867.3997802734375], "step": 0}]}, "val_loss": {"direction": "min", "observations": [{"value": [25392.72265625], "step": 0}]}, "val_mean_squared_error": {"direction": "min", "observations": [{"value": [25392.72265625], "step": 0}]}}}, "score": 1867.3997802734375, "best_step": 0, "status": "COMPLETED"}